minos/saga/__init__.py
minos/saga/context.py
minos/saga/definitions/__init__.py
minos/saga/definitions/operations.py
minos/saga/definitions/saga.py
minos/saga/definitions/steps/__init__.py
minos/saga/definitions/steps/abc.py
minos/saga/definitions/steps/conditional.py
minos/saga/definitions/steps/local.py
minos/saga/definitions/steps/remote.py
minos/saga/definitions/types.py
minos/saga/exceptions.py
minos/saga/executions/__init__.py
minos/saga/executions/commit.py
minos/saga/executions/executors/__init__.py
minos/saga/executions/executors/abc.py
minos/saga/executions/executors/local.py
minos/saga/executions/executors/request.py
minos/saga/executions/executors/response.py
minos/saga/executions/repositories/__init__.py
minos/saga/executions/repositories/abc.py
minos/saga/executions/repositories/database/__init__.py
minos/saga/executions/repositories/database/factories.py
minos/saga/executions/repositories/database/impl.py
minos/saga/executions/saga.py
minos/saga/executions/status.py
minos/saga/executions/steps/__init__.py
minos/saga/executions/steps/abc.py
minos/saga/executions/steps/conditional.py
minos/saga/executions/steps/local.py
minos/saga/executions/steps/remote.py
minos/saga/manager.py
minos/saga/messages.py
minos/saga/middleware.py
minos/saga/services.py
minos/saga/testing.py
minos/saga/utils.py
minos_microservice_saga-0.7.0.dist-info/LICENSE
minos_microservice_saga-0.7.0.dist-info/WHEEL
minos_microservice_saga-0.7.0.dist-info/METADATA
minos_microservice_saga-0.7.0.dist-info/RECORD
